<metadata>
<type>FAOStatProductionLivestockPrimary</type>
<periodTypeCode>yearly</periodTypeCode>
<abstractAbstract>The dataset contains data on livestock primary production and yelds. Producing/Slaughtered animals are given in head; except for poultry/birds/rabbits in 1000 head; bees in number. Yield/Carcass weight is given in Hg/Animal; except for eggs and poultry/birds/rabbits in 0.1 Grams/Animals; natural honey and beeswax in Hg/Beehive. Production is in tonnes. For additional information and general disclaimer, please refer to http://faostat.fao.org/site/569/default.aspx#ancor</abstractAbstract>
<keywords>faostat, production, stocks, livestock, primary</keywords>
<source country="0" contact="http://faostat.fao.org">FAOSTAT</source>
<provider country="0" contact="fabio.grita@fao.org">FENIX Workstation</provider>
<region>0</region>
<startDate>1960-01-01</startDate>
<endDate>2009-12-1001</endDate>
<dateLastUpdate>2010-12-12</dateLastUpdate>
<sharingCode>Public</sharingCode>
<categories>001</categories>
<title>FAOSTAT - Livestock Primary (Production)</title>
<code>FAOStatProductionLivestockPrimary</code>
<descriptors>
		<descriptor key="true">
			<header>Year</header>
			<contentDescriptor>date</contentDescriptor>
		</descriptor>
		<descriptor key="true">
			<header>Area Name</header>
			<contentDescriptor>featureCode</contentDescriptor>
			<options>
				<option>
					<name>Geographic</name>
					<value>FAOStatAreas</value>
					<region>0</region>
				</option>
			</options>
		</descriptor>
		<descriptor key="true">
			<header>Item Name</header>
			<contentDescriptor>commodityCode</contentDescriptor>
			<options>
				<option>
					<name>Indicator</name>
					<value>FAOStatItems</value>
					<region>0</region>
				</option>
			</options>
		</descriptor>
		<descriptor key="true">
			<header>Element Name</header>
			<contentDescriptor>firstIndicator</contentDescriptor>
			<options>
				<option>
					<name>Indicator</name>
					<value>FAOStatElements</value>
					<region>0</region>
				</option>
			</options>
		</descriptor>
		<descriptor key="false">
			<header>Value</header>
			<contentDescriptor>quantity</contentDescriptor>
		</descriptor>
		<descriptor key="true">
			<header>Flag</header>
			<contentDescriptor>secondIndicator</contentDescriptor>
			<options>
				<option>
					<name>Indicator</name>
					<value>FAOStatIFlags</value>
					<region>0</region>
				</option>
			</options>
		</descriptor>
		<descriptor key="true">
			<header>Measurement Unit</header>
			<contentDescriptor>measurementUnit</contentDescriptor>
		</descriptor>
	</descriptors>
</metadata>
